wyckoff/__init__.py
wyckoff/core.py
wyckoff/data/wyckoff.json
wyckoff-0.3.2.dist-info/METADATA
wyckoff-0.3.2.dist-info/WHEEL
wyckoff-0.3.2.dist-info/licenses/LICENSE
wyckoff-0.3.2.dist-info/RECORD
