Metadata-Version: 2.4
Name: wyckoff
Version: 0.3.2
Summary: A package for working with Wyckoff positions in crystallography
Project-URL: Repository, https://github.com/anoopkcn/wyckoff
Author-email: "Anoop K. Chandran" <anoopkcn@gmail.com>
License-File: LICENSE
Requires-Python: <3.13,>=3.10
Requires-Dist: sympy
